{"_type":"export","__export_format":4,"__export_date":"2022-12-07T12:16:22.764Z","__export_source":"insomnia.desktop.app:v2022.6.0","resources":[{"_id":"req_713388c6dda44923bd9662c64987aee6","parentId":"fld_34a559b36283409c8792a4e423d577ba","modified":1670377397929,"created":1670368231975,"url":"http://localhost:8080/medico","name":"Cadastrar","description":"","method":"POST","body":{"mimeType":"application/json","text":"{\n\t\"crm\": \"12234345\",\n\t\"cpf_medico\": \"115.701.800-92\",\n\t\"rg_medico\": \"29.585.651-9\",\n\t\"nome_medico\": \"Medico Fulano2\",\n\t\"sexo_medico\": \"H\",\n\t\"telefone_medico\": \"21333343536\",\n\t\"email_medico\": \"emailmedico2@gmail.com\",\n\t\"sangue_medico\": \"AB+\",\n\t\"nascimento_medico\": \"2000-10-11\",\n\t\"especialidade\": \"Acunpuntura\",\n\t\"senha\": \"senhamedico2\"\n}"},"parameters":[],"headers":[{"name":"Content-Type","value":"application/json"}],"authentication":{},"metaSortKey":-1670367710513,"isPrivate":false,"settingStoreCookies":true,"settingSendCookies":true,"settingDisableRenderRequestBody":false,"settingEncodeUrl":true,"settingRebuildPath":true,"settingFollowRedirects":"global","_type":"request"},{"_id":"fld_34a559b36283409c8792a4e423d577ba","parentId":"wrk_a7716dfad681477380c0392f7c316086","modified":1670367709080,"created":1670367709080,"name":"medico","description":"","environment":{},"environmentPropertyOrder":null,"metaSortKey":-1670367709080,"_type":"request_group"},{"_id":"wrk_a7716dfad681477380c0392f7c316086","parentId":null,"modified":1669551268258,"created":1669551268258,"name":"Arpamed","description":"","scope":"collection","_type":"workspace"},{"_id":"req_3bcd02c99b514f43a7438e34ceb1d024","parentId":"fld_34a559b36283409c8792a4e423d577ba","modified":1670380494429,"created":1670377064859,"url":"http://localhost:8080/medico","name":"Deletar","description":"","method":"DELETE","body":{"mimeType":"application/json","text":"{\n\t\"id\": 1\n}"},"parameters":[],"headers":[{"name":"Content-Type","value":"application/json"}],"authentication":{},"metaSortKey":-1670367710488,"isPrivate":false,"settingStoreCookies":true,"settingSendCookies":true,"settingDisableRenderRequestBody":false,"settingEncodeUrl":true,"settingRebuildPath":true,"settingFollowRedirects":"global","_type":"request"},{"_id":"req_f52d903af866431890e343e799569af0","parentId":"fld_34a559b36283409c8792a4e423d577ba","modified":1670368490585,"created":1670367710463,"url":"http://localhost:8080/medico/mostrar","name":"Listar","description":"","method":"GET","body":{},"parameters":[],"headers":[],"authentication":{},"metaSortKey":-1670367710463,"isPrivate":false,"settingStoreCookies":true,"settingSendCookies":true,"settingDisableRenderRequestBody":false,"settingEncodeUrl":true,"settingRebuildPath":true,"settingFollowRedirects":"global","_type":"request"},{"_id":"req_a53d64b56e07473da3331bf3f3e165de","parentId":"fld_25917194fca94a5c81613e6078d5d4e5","modified":1670352157276,"created":1669995297412,"url":"http://localhost:8080/paciente/mostrar","name":"Listar","description":"","method":"GET","body":{"mimeType":"application/json","text":""},"parameters":[],"headers":[{"name":"Content-Type","value":"application/json"}],"authentication":{},"metaSortKey":-1669990169756,"isPrivate":false,"settingStoreCookies":true,"settingSendCookies":true,"settingDisableRenderRequestBody":false,"settingEncodeUrl":true,"settingRebuildPath":true,"settingFollowRedirects":"global","_type":"request"},{"_id":"fld_25917194fca94a5c81613e6078d5d4e5","parentId":"wrk_a7716dfad681477380c0392f7c316086","modified":1669990148241,"created":1669990148241,"name":"paciente","description":"","environment":{},"environmentPropertyOrder":null,"metaSortKey":-1669990148241,"_type":"request_group"},{"_id":"req_e287203fd03c433497c3c6e10ec6cf58","parentId":"fld_25917194fca94a5c81613e6078d5d4e5","modified":1670352194356,"created":1670351741184,"url":"http://localhost:8080/paciente","name":"Deletar","description":"","method":"DELETE","body":{"mimeType":"application/json","text":""},"parameters":[],"headers":[{"name":"Content-Type","value":"application/json"}],"authentication":{},"metaSortKey":-1669990169731,"isPrivate":false,"settingStoreCookies":true,"settingSendCookies":true,"settingDisableRenderRequestBody":false,"settingEncodeUrl":true,"settingRebuildPath":true,"settingFollowRedirects":"global","_type":"request"},{"_id":"req_31fdbe54e53d4b8f85a890ee97c2c293","parentId":"fld_25917194fca94a5c81613e6078d5d4e5","modified":1670352588461,"created":1669990169706,"url":"http://localhost:8080/paciente","name":"Cadastrar","description":"","method":"POST","body":{"mimeType":"application/json","text":"{\n\t\"cpf_paciente\": \"664.405.280-05\",\n\t\"rg_paciente\": \"17.611.226-2\",\n\t\"nome_paciente\": \"Fulana de Tal2\",\n\t\"sexo_paciente\": \"H\",\n\t\"telefone_paciente\": \"5521991899884\",\n\t\"celular_paciente\": \"5521991899883\",\n\t\"sangue_paciente\": \"O-\",\n\t\"nascimento_paciente\": \"2000-10-11\",\n\t\"endereco_paciente\": \"Q25\",\n\t\"bairro_paciente\": \"Gramacho2\",\n\t\"cidade_paciente\": \"Duque de Caxias2\",\n\t\"uf_paciente\": \"SP\",\n\t\"cep_paciente\": \"123456781\",\n\t\"email_paciente\": \"fulaninha70@gmail.com\",\n\t\"nome_pai\": \"Bertano de Tal2\",\n\t\"nome_mae\": \"Ciclana de Tal2\"\n}"},"parameters":[],"headers":[{"name":"Content-Type","value":"application/json","id":"pair_24fc19e86962486d9d916bc159d835b4"},{"id":"pair_26de2db3c85042ddb3704c7df11ef102","name":"","value":"","description":""}],"authentication":{},"metaSortKey":-1669990169706,"isPrivate":false,"settingStoreCookies":true,"settingSendCookies":true,"settingDisableRenderRequestBody":false,"settingEncodeUrl":true,"settingRebuildPath":true,"settingFollowRedirects":"global","_type":"request"},{"_id":"env_22bac3a9caf86a7bc450a6e7c2df5d07c209b7ca","parentId":"wrk_a7716dfad681477380c0392f7c316086","modified":1669551268272,"created":1669551268272,"name":"Base Environment","data":{},"dataPropertyOrder":null,"color":null,"isPrivate":false,"metaSortKey":1669551268272,"_type":"environment"},{"_id":"jar_22bac3a9caf86a7bc450a6e7c2df5d07c209b7ca","parentId":"wrk_a7716dfad681477380c0392f7c316086","modified":1669551268274,"created":1669551268274,"name":"Default Jar","cookies":[],"_type":"cookie_jar"},{"_id":"spc_98f7b1aaf21745b4b3e2d7534ca50548","parentId":"wrk_a7716dfad681477380c0392f7c316086","modified":1669551268267,"created":1669551268267,"fileName":"Arpamed","contents":"","contentType":"yaml","_type":"api_spec"}]}